{"cameraMode":{"drawMode":0,"name":"Shaded","section":"Shading Mode"},"sceneLighting":true,"audioPlay":false,"sceneViewState":{"m_AlwaysRefresh":false,"showFog":true,"showSkybox":true,"showFlares":true,"showImageEffects":true,"showParticleSystems":true,"showVisualEffectGraphs":true,"m_FxEnabled":true},"in2DMode":false,"pivot":{"x":4.747954845428467,"y":5.829431056976318,"z":15.25754165649414},"rotation":{"x":-0.0021489134524017574,"y":0.9829059839248657,"z":-0.18374712765216828,"w":-0.011499288491904736},"size":0.7270742654800415,"orthographic":false}